account/__init__.py
account/admin.py
account/apps.py
account/converters.py
account/forms.py
account/managers.py
account/models.py
account/routers.py
account/serializers.py
account/tests.py
account/urls.py
account/views.py
account/viewsets.py
account/migrations/0001_initial.py
account/migrations/0002_auto_20180609_2350.py
account/migrations/__init__.py
djaccount-0.0.6b2.dist-info/METADATA
djaccount-0.0.6b2.dist-info/RECORD
djaccount-0.0.6b2.dist-info/WHEEL
djaccount-0.0.6b2.dist-info/top_level.txt
