Metadata-Version: 2.1
Name: djaccount
Version: 0.0.6b2
Summary: Django account manager
Home-page: https://gitlab.com/uda/djaccount
Author: Yehuda Deutsch
Author-email: yeh@uda.co.il
License: MIT
Keywords: django account
Platform: UNKNOWN
Classifier: Development Status :: 4 - Beta
Classifier: Environment :: Web Environment
Classifier: Framework :: Django
Classifier: Framework :: Django :: 2.0
Classifier: Intended Audience :: Developers
Classifier: License :: OSI Approved :: MIT License
Classifier: Natural Language :: English
Classifier: Operating System :: OS Independent
Classifier: Programming Language :: Python
Classifier: Programming Language :: Python :: 3
Classifier: Programming Language :: Python :: 3.6
Classifier: Topic :: Software Development :: Libraries
Classifier: Topic :: Software Development :: Libraries :: Python Modules
Classifier: Topic :: System :: Systems Administration :: Authentication/Directory
Requires-Python: >=3.6
Provides-Extra: dev
Provides-Extra: dev
Requires-Dist: django (>=2.0); extra == 'dev'
